README.rst
mcloud_simple_publish.py
setup.py
mcloud_plugin_simple_publish.egg-info/PKG-INFO
mcloud_plugin_simple_publish.egg-info/SOURCES.txt
mcloud_plugin_simple_publish.egg-info/dependency_links.txt
mcloud_plugin_simple_publish.egg-info/entry_points.txt
mcloud_plugin_simple_publish.egg-info/requires.txt
mcloud_plugin_simple_publish.egg-info/top_level.txt